{
  "kda": {
    "foundation": {
      "typography": {
        "font": {
          "h6": {
            "@xs": {
              "$name": "heading",
              "$description": "H6 Description",
              "$type": "typography",
              "$title": "H6",
              "$value": {
                "fontFamily": "{kda.foundation.typography.family.primaryFont}",
                "fontWeight": "{kda.foundation.typography.weight.primaryFont.bold}",
                "fontSize": "{kda.foundation.typography.fontSize.sm}",
                "letterSpacing": "{kda.foundation.spacing.no}",
                "lineHeight": "1.125rem"
              }
            },
            "@sm": {
              "$name": "heading",
              "$description": "H6 Description",
              "$type": "typography",
              "$title": "H6",
              "$value": {
                "fontFamily": "{kda.foundation.typography.family.primaryFont}",
                "fontWeight": "{kda.foundation.typography.weight.primaryFont.bold}",
                "fontSize": "{kda.foundation.typography.fontSize.sm}",
                "letterSpacing": "{kda.foundation.spacing.no}",
                "lineHeight": "1.125rem"
              }
            },
            "@md": {
              "$name": "heading",
              "$description": "H6 Description",
              "$type": "typography",
              "$title": "H6",
              "$value": {
                "fontFamily": "{kda.foundation.typography.family.primaryFont}",
                "fontWeight": "{kda.foundation.typography.weight.primaryFont.bold}",
                "fontSize": "{kda.foundation.typography.fontSize.sm}",
                "letterSpacing": "{kda.foundation.spacing.no}",
                "lineHeight": "1.125rem"
              }
            },
            "@lg": {
              "$name": "heading",
              "$description": "H6 Description",
              "$type": "typography",
              "$title": "H6",
              "$value": {
                "fontFamily": "{kda.foundation.typography.family.primaryFont}",
                "fontWeight": "{kda.foundation.typography.weight.primaryFont.bold}",
                "fontSize": "{kda.foundation.typography.fontSize.base}",
                "letterSpacing": "{kda.foundation.spacing.no}",
                "lineHeight": "{kda.foundation.typography.lineHeight.base}"
              }
            },
            "@xl": {
              "$name": "heading",
              "$description": "H6 Description",
              "$type": "typography",
              "$title": "H6",
              "$value": {
                "fontFamily": "{kda.foundation.typography.family.primaryFont}",
                "fontWeight": "{kda.foundation.typography.weight.primaryFont.bold}",
                "fontSize": "{kda.foundation.typography.fontSize.base}",
                "letterSpacing": "{kda.foundation.spacing.no}",
                "lineHeight": "{kda.foundation.typography.lineHeight.base}"
              }
            },
            "@xxl": {
              "$name": "heading",
              "$description": "H6 Description",
              "$type": "typography",
              "$title": "H6",
              "$value": {
                "fontFamily": "{kda.foundation.typography.family.primaryFont}",
                "fontWeight": "{kda.foundation.typography.weight.primaryFont.bold}",
                "fontSize": "{kda.foundation.typography.fontSize.base}",
                "letterSpacing": "{kda.foundation.spacing.no}",
                "lineHeight": "{kda.foundation.typography.lineHeight.base}"
              }
            }
          }
        }
      }
    }
  }
}