{
  "kda": {
    "foundation": {
      "color": {
        "semantic": {
          "positive": {
            "n0": {
              "$type": "color",
              "$value": "{kda.foundation.color.palette.lime.n0}"
            },
            "n1": {
              "$type": "color",
              "$value": "{kda.foundation.color.palette.lime.n1}"
            },
            "n5": {
              "$type": "color",
              "$value": "{kda.foundation.color.palette.lime.n5}"
            },
            "n10": {
              "$type": "color",
              "$value": "{kda.foundation.color.palette.lime.n10}"
            },
            "n20": {
              "$type": "color",
              "$value": "{kda.foundation.color.palette.lime.n20}"
            },
            "n30": {
              "$type": "color",
              "$value": "{kda.foundation.color.palette.lime.n30}"
            },
            "n40": {
              "$type": "color",
              "$value": "{kda.foundation.color.palette.lime.n40}"
            },
            "n50": {
              "$type": "color",
              "$value": "{kda.foundation.color.palette.lime.n50}"
            },
            "n60": {
              "$type": "color",
              "$value": "{kda.foundation.color.palette.lime.n60}"
            },
            "n70": {
              "$type": "color",
              "$value": "{kda.foundation.color.palette.lime.n70}"
            },
            "n80": {
              "$type": "color",
              "$value": "{kda.foundation.color.palette.lime.n80}"
            },
            "n90": {
              "$type": "color",
              "$value": "{kda.foundation.color.palette.lime.n90}"
            },
            "n95": {
              "$type": "color",
              "$value": "{kda.foundation.color.palette.lime.n95}"
            },
            "n99": {
              "$type": "color",
              "$value": "{kda.foundation.color.palette.lime.n99}"
            },
            "n100": {
              "$type": "color",
              "$value": "{kda.foundation.color.palette.lime.n100}"
            }
          }
        }
      }
    }
  }
}